setup.py
niti_distributions/Binomialdistribution.py
niti_distributions/Gaussiandistribution.py
niti_distributions/Generaldistribution.py
niti_distributions/__init__.py
niti_distributions.egg-info/PKG-INFO
niti_distributions.egg-info/SOURCES.txt
niti_distributions.egg-info/dependency_links.txt
niti_distributions.egg-info/not-zip-safe
niti_distributions.egg-info/top_level.txt